{
  "fist": {
    "id": "fist",
    "type": "weapon",
    "name": "Fists",
    "description": "Bare hands. Always available when no weapon is selected. Shield blocks it.",
    "damage": 5,
    "uses": null,
    "stackable": false,
    "breaksShield": false,
    "requirements": {
      "minDex": null,
      "dexGteTarget": false
    },
    "effects": {
      "blocksByShield": true
    },
    "icon": "👊"
  },
  "sword": {
    "id": "sword",
    "type": "weapon",
    "name": "Sword",
    "description": "A balanced blade. Shield blocks it.",
    "damage": 40,
    "uses": null,
    "stackable": false,
    "breaksShield": false,
    "requirements": {
      "minDex": null,
      "dexGteTarget": false
    },
    "effects": {
      "blocksByShield": true
    },
    "icon": "⚔️"
  },
  "club": {
    "id": "club",
    "type": "weapon",
    "name": "Club",
    "description": "A heavy blunt weapon. Shield blocks it.",
    "damage": 45,
    "uses": null,
    "stackable": false,
    "breaksShield": false,
    "requirements": {
      "minDex": null,
      "dexGteTarget": false
    },
    "effects": {
      "blocksByShield": true
    },
    "icon": "🪵"
  },
  "spear": {
    "id": "spear",
    "type": "weapon",
    "name": "Spear",
    "description": "Long reach. Shield blocks it.",
    "damage": 55,
    "uses": null,
    "stackable": false,
    "breaksShield": false,
    "requirements": {
      "minDex": null,
      "dexGteTarget": false
    },
    "effects": {
      "blocksByShield": true
    },
    "icon": "🗡️"
  },
  "trident": {
    "id": "trident",
    "type": "weapon",
    "name": "Trident",
    "description": "A brutal three-pronged weapon. Shield blocks it.",
    "damage": 60,
    "uses": null,
    "stackable": false,
    "breaksShield": false,
    "requirements": {
      "minDex": null,
      "dexGteTarget": false
    },
    "effects": {
      "blocksByShield": true
    },
    "icon": "🔱"
  },
  "axe": {
    "id": "axe",
    "type": "weapon",
    "name": "Axe",
    "description": "Can break a Shield (removes it, no damage that day).",
    "damage": 35,
    "uses": null,
    "stackable": false,
    "breaksShield": true,
    "requirements": {
      "minDex": null,
      "dexGteTarget": false
    },
    "effects": {
      "blocksByShield": false,
      "breaksShieldOnly": true
    },
    "icon": "🪓"
  },
  "wand": {
    "id": "wand",
    "type": "weapon",
    "name": "Wand",
    "description": "A simple wand. Shield blocks it.",
    "damage": 30,
    "uses": null,
    "stackable": false,
    "breaksShield": false,
    "requirements": {
      "minDex": null,
      "dexGteTarget": false
    },
    "effects": {
      "blocksByShield": true
    },
    "icon": "🪄"
  },
  "knife": {
    "id": "knife",
    "type": "weapon",
    "name": "Knife",
    "description": "Stackable. Each Knife adds +15 damage. Shield blocks it.",
    "damage": 15,
    "uses": null,
    "stackable": true,
    "breaksShield": false,
    "requirements": {
      "minDex": null,
      "dexGteTarget": false
    },
    "effects": {
      "blocksByShield": true
    },
    "icon": "🔪"
  },
  "dagger": {
    "id": "dagger",
    "type": "weapon",
    "name": "Dagger",
    "description": "Stackable. Each Dagger adds +15 damage. Can cut a Net once (then becomes useless). Shield blocks it.",
    "damage": 15,
    "uses": null,
    "stackable": true,
    "breaksShield": false,
    "requirements": {
      "minDex": null,
      "dexGteTarget": false
    },
    "effects": {
      "blocksByShield": true,
      "canCutNet": true
    },
    "icon": "🗡️"
  },
  "grenade": {
    "id": "grenade",
    "type": "weapon",
    "name": "Grenade",
    "description": "One-time use. Breaks Shield and still deals damage. Hurts the user. If target has higher Dexterity, target takes half damage.",
    "damage": 70,
    "uses": 1,
    "stackable": false,
    "breaksShield": true,
    "requirements": {
      "minDex": null,
      "dexGteTarget": false
    },
    "effects": {
      "blocksByShield": false,
      "penetratesShield": true,
      "selfDamage": 15,
    "halfIfTargetDexHigher": true,
    "splashDamage": 30,
    "splashIfOtherPercBelowTarget": true,
    "selfExtraDamageIfUserPercBelowTarget": 15
    },
    "icon": "💣"
  },
  "blowgun": {
    "id": "blowgun",
    "type": "weapon",
    "name": "Blowgun",
    "description": "Poisons the target (-10 HP per day) until cured by Medicine. Shield blocks it. Can be used twice per day.",
    "damage": 0,
    "uses": null,
    "stackable": false,
    "breaksShield": false,
    "requirements": {
      "minDex": null,
      "dexGteTarget": false
    },
    "effects": {
      "blocksByShield": true,
      "appliesPoison": true,
      "usesPerDay": 2
    },
    "icon": "🎯"
  },
  "bow": {
    "id": "bow",
    "type": "weapon",
    "name": "Bow & Arrows",
    "description": "65 damage. Requires Dexterity ≥ target's Dexterity. Shield blocks it. Starts with 3 arrows.",
    "damage": 65,
    "uses": 3,
    "stackable": false,
    "breaksShield": false,
    "requirements": {
      "minDex": null,
      "dexGteTarget": true
    },
    "effects": {
      "blocksByShield": true
    },
    "icon": "🏹"
  },
  "shield": {
    "id": "shield",
    "type": "protection",
    "name": "Shield",
    "description": "Blocks all weapons except Grenade and Axe. Using Shield means you cannot Attack today.",
    "damage": null,
    "uses": null,
    "stackable": false,
    "breaksShield": false,
    "requirements": {
      "minDex": null,
      "dexGteTarget": false
    },
    "effects": {},
    "icon": "🛡️"
  },
  "camouflage": {
    "id": "camouflage",
    "type": "consumable",
    "name": "Camouflage",
    "description": "One use. You become invisible in the area for a day: cannot be attacked, but can still attack. Does not protect against traps.",
    "damage": null,
    "uses": 1,
    "stackable": false,
    "breaksShield": false,
    "requirements": {
      "minDex": null,
      "dexGteTarget": false
    },
    "effects": {
      "invisibleOneDay": true,
      "nonTransferable": true
    },
    "icon": "🫥"
  },
  "flask": {
    "id": "flask",
    "type": "consumable",
    "name": "Flask",
    "description": "Unknown liquid. It could be Medicine or Poison. Revealed only when consumed.",
    "damage": null,
    "uses": 1,
    "stackable": false,
    "breaksShield": false,
    "requirements": {
      "minDex": null,
      "dexGteTarget": false
    },
    "effects": {
      "hidden": true,
      "revealOnUse": true
    },
    "icon": "🧪"
  },
  "net": {
    "id": "net",
    "type": "trap",
    "name": "Net",
    "description": "A trap that activates the next day. Captures everyone in the area except the owner and the highest Perception. Captured players are trapped for 2 days (no actions). A Dagger can cut the net, but the Dagger becomes useless.",
    "damage": 0,
    "uses": 1,
    "stackable": false,
    "breaksShield": false,
    "requirements": {},
    "effects": {
      "activatesNextDay": true,
      "trapKind": "net"
    },
    "icon": "🕸️"
  },
  "mine": {
    "id": "mine",
    "type": "trap",
    "name": "Mine",
    "description": "A trap that activates the next day. Deals 60 damage to the lowest Perception who enter or remain in the area (ties: all take damage). The whole arena learns there was an accident, but the area is not revealed. Death by mine drops all items on the ground (no spoils).",
    "damage": 60,
    "uses": 1,
    "stackable": false,
    "breaksShield": false,
    "requirements": {},
    "effects": {
      "activatesNextDay": true,
      "trapKind": "mine"
    },
    "icon": "🧨"
  },
  "backpack": {
    "id": "backpack",
    "type": "utility",
    "name": "Backpack",
    "description": "Contains 2–3 items. Disappears after opening.",
    "damage": null,
    "uses": 1,
    "stackable": false,
    "breaksShield": false,
    "requirements": {
      "minDex": null,
      "dexGteTarget": false
    },
    "effects": {
      "opensIntoLoot": true
    },
    "icon": "🎒"
  },
  "wild_fruits": {
    "id": "wild_fruits",
    "type": "consumable",
    "name": "Wild Fruits",
    "icon": "🍓",
    "description": "Restores 10 FP immediately when collected.",
    "damage": null,
    "uses": 1,
    "stackable": false,
    "breaksShield": false,
    "requirements": {},
    "effects": {
      "autoConsumeOnCollect": true,
      "healFP": 10
    }
  },
  "edible_roots": {
    "id": "edible_roots",
    "type": "consumable",
    "name": "Edible Roots",
    "icon": "🥕",
    "description": "Restores 15 FP immediately when collected.",
    "damage": null,
    "uses": 1,
    "stackable": false,
    "breaksShield": false,
    "requirements": {},
    "effects": {
      "autoConsumeOnCollect": true,
      "healFP": 15
    }
  },
  "freshwater_fish": {
    "id": "freshwater_fish",
    "type": "consumable",
    "name": "Freshwater Fish",
    "icon": "🐟",
    "description": "Restores 20 FP immediately when collected.",
    "damage": null,
    "uses": 1,
    "stackable": false,
    "breaksShield": false,
    "requirements": {},
    "effects": {
      "autoConsumeOnCollect": true,
      "healFP": 20
    }
  },
  "capital_ration": {
    "id": "capital_ration",
    "type": "consumable",
    "name": "Capital Ration",
    "icon": "🥫",
    "description": "Restores 40 FP immediately when collected. Rare.",
    "damage": null,
    "uses": 1,
    "stackable": false,
    "breaksShield": false,
    "requirements": {},
    "effects": {
      "autoConsumeOnCollect": true,
      "healFP": 40,
      "rare": true
    }
  },
  "first_aid_backpack": {
    "id": "first_aid_backpack",
    "type": "consumable",
    "name": "First Aid Backpack",
    "icon": "🧰",
    "description": "Restores 30 HP and cures poison immediately when collected.",
    "damage": null,
    "uses": 1,
    "stackable": false,
    "breaksShield": false,
    "requirements": {},
    "effects": {
      "autoConsumeOnCollect": true,
      "healHP": 30,
      "curePoison": true
    }
  },
  "survival_kit": {
    "id": "survival_kit",
    "type": "consumable",
    "name": "Survival Kit",
    "icon": "🧷",
    "description": "Restores 20 HP and prevents being trapped once (next trap only).",
    "damage": null,
    "uses": 1,
    "stackable": false,
    "breaksShield": false,
    "requirements": {},
    "effects": {
      "autoConsumeOnCollect": true,
      "healHP": 20,
      "preventTrapOnce": true
    }
  },
  "stimulant": {
    "id": "stimulant",
    "type": "consumable",
    "name": "Stimulant",
    "icon": "💉",
    "description": "Ignores one movement block today.",
    "damage": null,
    "uses": 1,
    "stackable": false,
    "breaksShield": false,
    "requirements": {},
    "effects": {
      "autoConsumeOnCollect": true,
      "ignoreMoveBlockToday": true
    }
  }
}